promptflow/__init__.py
promptflow/client.py
promptflow/llm.py
promptflow_ai-0.1.0.dist-info/licenses/LICENSE
promptflow_ai-0.1.0.dist-info/METADATA
promptflow_ai-0.1.0.dist-info/WHEEL
promptflow_ai-0.1.0.dist-info/top_level.txt
promptflow_ai-0.1.0.dist-info/RECORD
