Metadata-Version: 2.4
Name: promptflow-ai
Version: 0.1.0
Summary: Agentic AI infrastructure for tracking LLM performance and prompt accuracy
Home-page: https://github.com/promptflow/promptflow-ai
Author: PromptFlow
Author-email: PromptFlow <hello@promptflow.dev>
License: MIT
Project-URL: Homepage, https://promptflow-ui.vercel.app
Project-URL: Documentation, https://promptflow-ui.vercel.app
Project-URL: Repository, https://github.com/promptflow/promptflow-ai
Project-URL: Issues, https://github.com/promptflow/promptflow-ai/issues
Keywords: ai,agentic-ai,llm,prompts,tracking,analytics,openai,anthropic,monitoring
Classifier: Development Status :: 3 - Alpha
Classifier: Intended Audience :: Developers
Classifier: License :: OSI Approved :: MIT License
Classifier: Programming Language :: Python :: 3
Classifier: Programming Language :: Python :: 3.8
Classifier: Programming Language :: Python :: 3.9
Classifier: Programming Language :: Python :: 3.10
Classifier: Programming Language :: Python :: 3.11
Classifier: Programming Language :: Python :: 3.12
Requires-Python: >=3.8
License-File: LICENSE
Requires-Dist: requests>=2.25.0
Provides-Extra: dev
Requires-Dist: pytest>=7.0.0; extra == "dev"
Requires-Dist: black>=22.0.0; extra == "dev"
Requires-Dist: mypy>=0.950; extra == "dev"
Dynamic: author
Dynamic: home-page
Dynamic: license-file
Dynamic: requires-python
